README.txt
setup.py
collective/__init__.py
collective.portlet.filtersearch.egg-info/PKG-INFO
collective.portlet.filtersearch.egg-info/SOURCES.txt
collective.portlet.filtersearch.egg-info/dependency_links.txt
collective.portlet.filtersearch.egg-info/entry_points.txt
collective.portlet.filtersearch.egg-info/namespace_packages.txt
collective.portlet.filtersearch.egg-info/not-zip-safe
collective.portlet.filtersearch.egg-info/requires.txt
collective.portlet.filtersearch.egg-info/top_level.txt
collective/portlet/__init__.py
collective/portlet/filtersearch/__init__.py
collective/portlet/filtersearch/configure.zcml
collective/portlet/filtersearch/styles.css
collective/portlet/filtersearch/tests.py
collective/portlet/filtersearch/version.txt
collective/portlet/filtersearch/portlets/__init__.py
collective/portlet/filtersearch/portlets/configure.zcml
collective/portlet/filtersearch/portlets/filtersearch.pt
collective/portlet/filtersearch/portlets/filtersearch.py
collective/portlet/filtersearch/profiles/default/cssregistry.xml
collective/portlet/filtersearch/profiles/default/metadata.xml
collective/portlet/filtersearch/profiles/default/portlets.xml
docs/HISTORY.txt
docs/INSTALL.txt
docs/LICENSE.GPL
docs/LICENSE.txt