Metadata-Version: 1.0
Name: collective.portlet.filtersearch
Version: 0.2
Summary: Shows a definable filter portlet that allows to filter search results
Home-page: http://pypi.python.org/pypi/collective.portlet.filtersearch
Author: Matous Hora
Author-email: matous.hora@dms4u.cz
License: GPL
Keywords: plone portlet search
Platform: UNKNOWN
Classifier: Framework :: Plone
Classifier: Programming Language :: Python
